aioautomower/__init__.py
aioautomower/auth.py
aioautomower/commands.py
aioautomower/const.py
aioautomower/exceptions.py
aioautomower/model/__init__.py
aioautomower/model/model.py
aioautomower/model/model_battery.py
aioautomower/model/model_calendar.py
aioautomower/model/model_capabilities.py
aioautomower/model/model_metadata.py
aioautomower/model/model_mower.py
aioautomower/model/model_planner.py
aioautomower/model/model_positions.py
aioautomower/model/model_settings.py
aioautomower/model/model_statistics.py
aioautomower/model/model_stay_out_zones.py
aioautomower/model/model_system.py
aioautomower/model/model_token.py
aioautomower/model/model_work_areas.py
aioautomower/model/utils.py
aioautomower/model_input/__init__.py
aioautomower/model_input/model_event.py
aioautomower/model_input/model_rest.py
aioautomower/py.typed
aioautomower/session.py
aioautomower/timeline.py
aioautomower/tz_util.py
aioautomower/utils.py
aioautomower-2025.6.0.dist-info/LICENSE
aioautomower-2025.6.0.dist-info/METADATA
aioautomower-2025.6.0.dist-info/WHEEL
aioautomower-2025.6.0.dist-info/RECORD
