Metadata-Version: 2.3
Name: aioautomower
Version: 2025.6.0
Summary: MPython module to talk to Husqvarna Automower.
License: MIT
Keywords: Husqvarna,Automower,api,async,client
Author: Thomas Peter Protzner
Author-email: thomas.protzner@gmail.com
Requires-Python: >=3.11,<4.0
Classifier: Development Status :: 5 - Production/Stable
Classifier: Framework :: AsyncIO
Classifier: Intended Audience :: Developers
Classifier: License :: OSI Approved :: MIT License
Classifier: Natural Language :: English
Classifier: Programming Language :: Python :: 3
Classifier: Programming Language :: Python :: 3.11
Classifier: Programming Language :: Python :: 3.12
Classifier: Programming Language :: Python :: 3.13
Classifier: Topic :: Software Development :: Libraries :: Python Modules
Requires-Dist: PyJWT (>=2.8.0,<3.0.0)
Requires-Dist: aiohttp (>=3.9.3,<4.0.0)
Requires-Dist: ical (>=8.0.1)
Requires-Dist: mashumaro (>=3.12,<4.0)
Requires-Dist: python-dateutil (>=2.9.0-post.0,<3.0.0)
Requires-Dist: tzlocal (>=5.2,<6.0)
Project-URL: Documentation, https://github.com/Thomas55555/aioautomower
Project-URL: Homepage, https://github.com/Thomas55555/aioautomower
Project-URL: Issues, https://github.com/Thomas55555/aioautomower/issues
Project-URL: Repository, https://github.com/Thomas55555/aioautomower
